loglikelihood_estimator/__init__.py
loglikelihood_estimator/estimator.py
loglikelihood_estimator/utils.py
loglikelihood_estimator_1-0.1.0.dist-info/METADATA
loglikelihood_estimator_1-0.1.0.dist-info/WHEEL
loglikelihood_estimator_1-0.1.0.dist-info/top_level.txt
loglikelihood_estimator_1-0.1.0.dist-info/RECORD
